{    "id":"BrainStorm",    "name":"BrainStorm",    "description":"",    "bst_db_path":"C:/Users/Ariosky/.brainstorm/local_db/HeadModel_CHBM_DistC_005",    "modality":"EEG",    "preprocessed_data":{        "base_path":"E:/Data/CHBM/Pedrito/EEG",        "file_location":"SubID.mat",        "format":"mat",        "clean_data":{            "run":true,            "toolbox":"eeglab",            "toolbox_path":"D:/Develop/EEGLab_Test/eeglab2020_0",            "max_freq":52,            "read_marks":false        },        "labels_file_path":"app/common_labels_pedrito.json"    }}